labyrinth/LabGame.py
labyrinth/Labyrinth.py
labyrinth/Player.py
labyrinth/Text_Display.py
labyrinth/__init__.py
labyrinth/sprites/end_rect.png
labyrinth/sprites/panda_player.png
labyrinth/sprites/wall.png
labyrinth/test/__init__.py
labyrinth/test/test_LabGame.py
labyrinth/test/test_Labyrinth.py
labyrinth/test/test_Player.py
labyrinth/test/test_Text_Display.py
labyrinth-0.1.1.data/scripts/labyrinth
labyrinth-0.1.1.dist-info/DESCRIPTION.rst
labyrinth-0.1.1.dist-info/METADATA
labyrinth-0.1.1.dist-info/RECORD
labyrinth-0.1.1.dist-info/WHEEL
labyrinth-0.1.1.dist-info/metadata.json
labyrinth-0.1.1.dist-info/top_level.txt
