Metadata-Version: 2.0
Name: labyrinth
Version: 0.1.1
Summary: Simple labyrinth game
Home-page: UNKNOWN
Author: Tian Yen
Author-email: tianchu@uw.edu
License: LICENSE.txt
Platform: UNKNOWN
